colav_protobuf_utils/__about__.py
colav_protobuf_utils/__init__.py
colav_protobuf_utils/deserialization/__init__.py
colav_protobuf_utils/deserialization/deserializer.py
colav_protobuf_utils/protobuf_generator/__init__.py
colav_protobuf_utils/protobuf_generator/agent_update.py
colav_protobuf_utils/protobuf_generator/automaton_output.py
colav_protobuf_utils/protobuf_generator/collision_metrics.py
colav_protobuf_utils/protobuf_generator/controller_feedback.py
colav_protobuf_utils/protobuf_generator/mapMetaData.py
colav_protobuf_utils/protobuf_generator/mission_request.py
colav_protobuf_utils/protobuf_generator/mission_response.py
colav_protobuf_utils/protobuf_generator/obstacles_update.py
colav_protobuf_utils/protobuf_generator/proto_creator.py
colav_protobuf_utils/protobuf_generator/stamp.py
colav_protobuf_utils/protobuf_generator/unsafe_set.py
colav_protobuf_utils/protobuf_generator/vessel_generator.py
colav_protobuf_utils/serialization/__init__.py
colav_protobuf_utils/serialization/serializer.py
colav_protobuf_utils-0.2.0.dist-info/METADATA
colav_protobuf_utils-0.2.0.dist-info/WHEEL
colav_protobuf_utils-0.2.0.dist-info/licenses/LICENSE.txt
colav_protobuf_utils-0.2.0.dist-info/RECORD
