Metadata-Version: 2.4
Name: colav-protobuf-utils
Version: 0.2.0
Summary: A package to simplify the generation, serialization, and deserialization of COLAV Protobuf messages.
Project-URL: Documentation, https://github.com/Ryan/colav-protobuf-utils#readme
Project-URL: Issues, https://github.com/Ryan/colav-protobuf-utils/issues
Project-URL: Source, https://github.com/Ryan/colav-protobuf-utils
Author-email: Ryan <r.mckee@qub.ac.uk>
License-Expression: MIT
License-File: LICENSE.txt
Classifier: Development Status :: 4 - Beta
Classifier: Programming Language :: Python
Classifier: Programming Language :: Python :: 3.8
Classifier: Programming Language :: Python :: 3.9
Classifier: Programming Language :: Python :: 3.10
Classifier: Programming Language :: Python :: 3.11
Classifier: Programming Language :: Python :: 3.12
Classifier: Programming Language :: Python :: Implementation :: CPython
Classifier: Programming Language :: Python :: Implementation :: PyPy
Requires-Python: >=3.8
Requires-Dist: colav-protobuf==0.2.4
Requires-Dist: hatch
Requires-Dist: numpy
Requires-Dist: pytest
Requires-Dist: shapely
